suitesparse_graphblas.libs/libgraphblas-1f31f0e3.so.10.1.1
suitesparse_graphblas.libs/libgomp-ba615989.so.1.0.0
suitesparse_graphblas-10.1.1.0.dist-info/METADATA
suitesparse_graphblas-10.1.1.0.dist-info/LICENSE
suitesparse_graphblas-10.1.1.0.dist-info/top_level.txt
suitesparse_graphblas-10.1.1.0.dist-info/WHEEL
suitesparse_graphblas-10.1.1.0.dist-info/RECORD
suitesparse_graphblas/utils.pxd
suitesparse_graphblas/matrix.py
suitesparse_graphblas/utils.pyx
suitesparse_graphblas/_graphblas.abi3.so
suitesparse_graphblas/create_headers.py
suitesparse_graphblas/__init__.py
suitesparse_graphblas/utils.c
suitesparse_graphblas/suitesparse_graphblas_no_complex.h
suitesparse_graphblas/source.c
suitesparse_graphblas/exceptions.py
suitesparse_graphblas/vector.py
suitesparse_graphblas/scalar.py
suitesparse_graphblas/utils.cpython-312-x86_64-linux-musl.so
suitesparse_graphblas/suitesparse_graphblas.h
suitesparse_graphblas/tests/test_package.py
suitesparse_graphblas/tests/test_scalar.py
suitesparse_graphblas/tests/__init__.py
suitesparse_graphblas/tests/test_exceptions.py
suitesparse_graphblas/tests/test_doctest.py
suitesparse_graphblas/tests/test_io.py
suitesparse_graphblas/tests/test_jit.py
suitesparse_graphblas/tests/test_initialize.py
suitesparse_graphblas/tests/conftest.py
suitesparse_graphblas/io/__init__.py
suitesparse_graphblas/io/serialize.py
suitesparse_graphblas/io/binary.py
