Metadata-Version: 2.1
Name: suitesparse-graphblas
Version: 10.1.1.0
Summary: SuiteSparse:GraphBLAS Python bindings.
Author: Jim Kitchen, Michel Pelletier, suitesparse-graphblas contributors
Author-email: Erik Welch <erik.n.welch@gmail.com>
Maintainer-email: Erik Welch <erik.n.welch@gmail.com>, Jim Kitchen <jim22k@gmail.com>, Michel Pelletier <michel@graphegon.com>, Adam Lugowski <alugowski@gmail.com>
License: Apache License
Project-URL: homepage, https://github.com/GraphBLAS/python-suitesparse-graphblas
Project-URL: repository, https://github.com/GraphBLAS/python-suitesparse-graphblas
Project-URL: changelog, https://github.com/GraphBLAS/python-suitesparse-graphblas/releases
Keywords: graphblas,graph,sparse,matrix,lagraph,suitesparse,Networks,Graph Theory,Mathematics,network,discrete mathematics,math
Classifier: Development Status :: 5 - Production/Stable
Classifier: License :: OSI Approved :: Apache Software License
Classifier: Operating System :: MacOS :: MacOS X
Classifier: Operating System :: POSIX :: Linux
Classifier: Operating System :: Microsoft :: Windows
Classifier: Programming Language :: Python
Classifier: Programming Language :: Python :: 3
Classifier: Programming Language :: Python :: 3.9
Classifier: Programming Language :: Python :: 3.10
Classifier: Programming Language :: Python :: 3.11
Classifier: Programming Language :: Python :: 3.12
Classifier: Programming Language :: Python :: 3.13
Classifier: Programming Language :: Python :: 3 :: Only
Classifier: Intended Audience :: Developers
Classifier: Intended Audience :: Other Audience
Classifier: Intended Audience :: Science/Research
Classifier: Topic :: Scientific/Engineering
Classifier: Topic :: Scientific/Engineering :: Information Analysis
Classifier: Topic :: Scientific/Engineering :: Mathematics
Classifier: Topic :: Software Development :: Libraries :: Python Modules
Requires-Python: >=3.9
License-File: LICENSE
Requires-Dist: cffi>=1.15
Requires-Dist: numpy>=1.23
Provides-Extra: test
Requires-Dist: pytest; extra == "test"
